[200,"OK",[{"abstract":"script for generating site maps","author":"AWRIGLEY","date":"1999-03-31T18:55:57","distribution":"sitemapper","first":"","maturity":"released","release":"sitemapper-1.008","status":"backpan","version":"1.008"},{"abstract":"configurable web traversal engine (for web robots & agents)","author":"AWRIGLEY","date":"1999-03-31T18:54:25","distribution":"WWW-Robot","first":1,"maturity":"released","release":"WWW-Robot-0.017","status":"backpan","version":"0.017"},{"abstract":"mail utility functions","author":"GBARR","date":"1999-03-31T17:45:02","distribution":"MailTools","first":"","maturity":"released","release":"MailTools-1.13","status":"backpan","version":"1.13"},{"abstract":"convert Bourne shell script to Perl program","author":"MERLYN","date":"1999-03-31T12:55:18","distribution":"sh2perl","first":"","maturity":"released","release":"sh2perl-0.03","status":"backpan","version":"0.03"},{"abstract":"Perl extension for blah blah blah","author":"RSAVAGE","date":"1999-03-31T11:02:12","distribution":"X500-DN","first":"","maturity":"released","release":"X500-DN-1.11","status":"backpan","version":"1.11"},{"abstract":"Provide a simple interface to CVS (the Concurrent Versions System).","author":"RSAVAGE","date":"1999-03-31T11:02:11","distribution":"VCS-CVS","first":"","maturity":"released","release":"VCS-CVS-1.02","status":"backpan","version":"1.02"},{"abstract":"Determine the infinitive form of a conjugated word","author":"RSAVAGE","date":"1999-03-31T11:02:09","distribution":"Lingua-EN-Infinitive","first":"","maturity":"released","release":"Lingua-EN-Infinitive-1.01","status":"backpan","version":"1.01"},{"abstract":"Provide a simple wrapper around Getopt::Long.","author":"RSAVAGE","date":"1999-03-31T11:02:08","distribution":"Getopt-Simple","first":"","maturity":"released","release":"Getopt-Simple-1.41","status":"backpan","version":"1.41"},{"abstract":"A Discrete Finite Automata command processor.","author":"RSAVAGE","date":"1999-03-31T11:00:36","distribution":"DFA-Command","first":"","maturity":"released","release":"DFA-Command-1.92","status":"backpan","version":"1.92"},{"abstract":"Print a C++ class hierarchy.","author":"RSAVAGE","date":"1999-03-31T11:00:35","distribution":"Class-Tree","first":"","maturity":"released","release":"Class-Tree-1.11","status":"backpan","version":"1.11"},{"abstract":"Bind Perl structures to text files","author":"EHOOD","date":"1999-03-31T06:33:22","distribution":"Text-Bind","first":"","maturity":"released","release":"Text-Bind-0.02","status":"backpan","version":"0.02"},{"abstract":null,"author":"HORROCKS","date":"1999-03-30T21:44:13","distribution":"CGI-SpeedyCGI","first":"","maturity":"released","release":"CGI-SpeedyCGI-1.5","status":"backpan","version":"1.5"},{"abstract":"Perl extension for Compatibility Infos about DBD Drivers","author":"GRICHTER","date":"1999-03-30T21:31:58","distribution":"DBIx-Recordset","first":"","maturity":"released","release":"DBIx-Recordset-0.19-beta","status":"backpan","version":"0.19"},{"abstract":null,"author":"BHOLZMAN","date":"1999-03-30T21:15:09","distribution":"pop","first":1,"maturity":"released","release":"pop-0.01","status":"backpan","version":"0.01"},{"abstract":null,"author":"FHOLTRY","date":"1999-03-30T18:41:55","distribution":"ppl-plug","first":1,"maturity":"released","release":"ppl-plug-0.94","status":"cpan","version":"0.94"},{"abstract":"Make event loop statistics easily available","author":"JPRIT","date":"1999-03-30T18:34:54","distribution":"NetServer-ProcessTop","first":"","maturity":"released","release":"NetServer-ProcessTop-0.96","status":"backpan","version":"0.96"},{"abstract":"Event loop statistics","author":"JPRIT","date":"1999-03-30T18:30:53","distribution":"Event-Stats","first":"","maturity":"released","release":"Event-Stats-0.5","status":"backpan","version":"0.5"},{"abstract":"Event loop processing","author":"JPRIT","date":"1999-03-30T18:26:52","distribution":"Event","first":"","maturity":"released","release":"Event-0.33","status":"backpan","version":"0.33"},{"abstract":"module to truncate Japanese encoded text.","author":"AWRIGLEY","date":"1999-03-30T10:18:21","distribution":"HTML-Summary","first":"","maturity":"released","release":"HTML-Summary-0.015","status":"backpan","version":"0.015"},{"abstract":"v.0.23 General purpose text/data merging methods in Perl.","author":"SHARRIS","date":"1999-03-30T06:52:59","distribution":"Text-Merge","first":"","maturity":"released","release":"Text-Merge-0.23","status":"backpan","version":"0.23"},{"abstract":"Perl 5 module to talk to NNTP (RFC977) server","author":"RVA","date":"1999-03-29T23:53:50","distribution":"NNTPClient","first":"","maturity":"released","release":"NNTPClient-0.32","status":"backpan","version":"0.32"},{"abstract":"a font dialog widget for perl/Tk","author":"SREZIC","date":"1999-03-29T18:40:18","distribution":"Tk-FontDialog","first":"","maturity":"released","release":"Tk-FontDialog-0.03","status":"backpan","version":"0.03"},{"abstract":null,"author":"KJALB","date":"1999-03-29T16:29:09","distribution":"Devel-PPPort","first":"","maturity":"released","release":"Devel-PPPort-1.0007","status":"cpan","version":"1.0007"},{"abstract":"provide auto-configuration utilities","author":"KJALB","date":"1999-03-29T16:24:37","distribution":"TermReadKey","first":"","maturity":"released","release":"TermReadKey-2.14","status":"backpan","version":"2.14"},{"abstract":null,"author":"HORROCKS","date":"1999-03-29T13:44:38","distribution":"CGI-SpeedyCGI","first":1,"maturity":"released","release":"CGI-SpeedyCGI-1.4","status":"backpan","version":"1.4"},{"abstract":"process embedded perl in HTML in the OutputChain","author":"CHOLET","date":"1999-03-29T09:44:30","distribution":"Apache-EmbperlChain","first":"","maturity":"released","release":"Apache-EmbperlChain-0.03","status":"backpan","version":"0.03"},{"abstract":"Low-level support for Perl embedded in GNU Emacs","author":"JTOBEY","date":"1999-03-29T01:11:53","distribution":"Emacs-Lisp","first":"","maturity":"released","release":"Emacs-Lisp-0.90","status":"backpan","version":"0.90"},{"abstract":"converts a collection of POD pages to HTML format.","author":"GBARR","date":"1999-03-29T00:50:43","distribution":"perl","first":"","maturity":"released","release":"perl5.005_03","status":"cpan","version":"5.005_03"},{"abstract":"HTML validator","author":"SAIT","date":"1999-03-28T21:48:19","distribution":"HTML-Validator","first":"","maturity":"released","release":"HTML-Validator-0.07","status":"backpan","version":"0.07"},{"abstract":null,"author":"JTOBEY","date":"1999-03-28T20:57:03","distribution":"Emacs-PerlmacsPatch","first":"","maturity":"released","release":"Emacs-PerlmacsPatch-0.12","status":"backpan","version":"0.12"},{"abstract":null,"author":"MIVKOVIC","date":"1999-03-28T16:48:01","distribution":"Mail-Sendmail","first":"","maturity":"released","release":"Mail-Sendmail-0.77","status":"backpan","version":"0.77"},{"abstract":"Attribute class","author":"PSHARPE","date":"1999-03-28T15:17:21","distribution":"DbFramework","first":"","maturity":"released","release":"DbFramework-1.07","status":"backpan","version":"1.07"},{"abstract":"Structured text base class","author":"PSHARPE","date":"1999-03-28T12:49:38","distribution":"TextStructured","first":1,"maturity":"released","release":"TextStructured-0.02","status":"latest","version":"0.02"},{"abstract":"parse, manipulate and lookup IP network blocks","author":"MUIR","date":"1999-03-28T03:32:00","distribution":"Net-Netmask","first":"","maturity":"released","release":"Net-Netmask-1.6","status":"backpan","version":"1.6"},{"abstract":null,"author":"MIVKOVIC","date":"1999-03-27T23:07:49","distribution":"Mail-Sendmail","first":"","maturity":"released","release":"Mail-Sendmail-0.76","status":"backpan","version":"0.76"},{"abstract":"Perl extension for writing Gimp Extensions/Plug-ins/Load & Save-Handlers","author":"MLEHMANN","date":"1999-03-27T20:06:54","distribution":"Gimp","first":"","maturity":"released","release":"Gimp-1.072","status":"backpan","version":"1.072"},{"abstract":"Generate Recursive-Descent Parsers","author":"DCONWAY","date":"1999-03-27T20:06:53","distribution":"Parse-RecDescent","first":"","maturity":"released","release":"Parse-RecDescent-1.64","status":"backpan","version":"1.64"},{"abstract":null,"author":"MIVKOVIC","date":"1999-03-27T18:19:51","distribution":"Mail-Sendmail","first":"","maturity":"released","release":"Mail-Sendmail-0.75","status":"backpan","version":"0.75"},{"abstract":"Module for Conjugating Portuguese verbs","author":"EGROSS","date":"1999-03-27T18:04:02","distribution":"Lingua-PT-Conjugate","first":"","maturity":"released","release":"Lingua-PT-Conjugate-0.93","status":"backpan","version":"0.93"},{"abstract":"Perl libraries for the Hotline internet client","author":"JSIRACUSA","date":"1999-03-27T16:53:10","distribution":"Net-Hotline","first":"","maturity":"released","release":"Net-Hotline-0.73","status":"backpan","version":"0.73"},{"abstract":null,"author":"JTOBEY","date":"1999-03-27T16:39:29","distribution":"Emacs-PerlmacsPatch","first":"","maturity":"released","release":"Emacs-PerlmacsPatch-0.11","status":"backpan","version":"0.11"},{"abstract":null,"author":"RSAVAGE","date":"1999-03-27T06:52:35","distribution":"X500-DN","first":"","maturity":"released","release":"X500-DN-1.10","status":"backpan","version":"1.10"},{"abstract":"Provide a simple interface to CVS (the Concurrent Versions System).","author":"RSAVAGE","date":"1999-03-27T06:52:34","distribution":"VCS-CVS","first":"","maturity":"released","release":"VCS-CVS-1.01","status":"backpan","version":"1.01"},{"abstract":"Provide a simple wrapper around Getopt::Long.","author":"RSAVAGE","date":"1999-03-27T06:51:03","distribution":"Getopt-Simple","first":"","maturity":"released","release":"Getopt-Simple-1.40","status":"backpan","version":"1.40"},{"abstract":"Print a directory hierarchy.","author":"RSAVAGE","date":"1999-03-27T06:51:02","distribution":"Class-Tree","first":"","maturity":"released","release":"Class-Tree-1.10","status":"backpan","version":"1.10"},{"abstract":"Convert an XML file into a suite of CGI forms.","author":"RSAVAGE","date":"1999-03-27T06:51:00","distribution":"CGI-Formalware","first":"","maturity":"released","release":"CGI-Formalware-1.04","status":"backpan","version":"1.04"},{"abstract":"interpolates script options from files into @ARGV","author":"JSTENZEL","date":"1999-03-26T23:18:42","distribution":"Getopt-ArgvFile","first":"","maturity":"released","release":"Getopt-ArgvFile-1.01","status":"cpan","version":"1.01"},{"abstract":"Perl access to utmp-style databases","author":"MPIOTR","date":"1999-03-26T20:52:29","distribution":"User-Utmp","first":"","maturity":"released","release":"User-Utmp-0.02","status":"backpan","version":"0.02"},{"abstract":"general-purpose wrapper for cleartool program","author":"DSB","date":"1999-03-26T16:46:46","distribution":"ClearCase-Ct","first":"","maturity":"released","release":"ClearCase-Ct-1.15","status":"backpan","version":"1.15"},{"abstract":"Perl interface to the MD5 Algorithm","author":"GAAS","date":"1999-03-26T13:51:38","distribution":"Digest-MD5","first":"","maturity":"released","release":"Digest-MD5-2.06","status":"backpan","version":"2.06"},{"abstract":"Uniform Resource Identifiers (absolute and relative)","author":"GAAS","date":"1999-03-26T13:50:04","distribution":"URI","first":"","maturity":"released","release":"URI-1.02","status":"backpan","version":"1.02"},{"abstract":"base class for objects that can read and write text lines","author":"JV","date":"1999-03-26T09:09:07","distribution":"Text-Filter","first":"","maturity":"released","release":"Text-Filter-1.7","status":"backpan","version":"1.7"},{"abstract":null,"author":"JTOBEY","date":"1999-03-26T07:34:08","distribution":"Emacs-PerlmacsPatch","first":1,"maturity":"released","release":"Emacs-PerlmacsPatch-0.10","status":"backpan","version":"0.10"},{"abstract":"Generate Recursive-Descent Parsers","author":"DCONWAY","date":"1999-03-26T02:05:26","distribution":"Parse-RecDescent","first":"","maturity":"released","release":"Parse-RecDescent-1.63","status":"backpan","version":"1.63"},{"abstract":"Perl module for manipulating a password file stored in a BerkeleyDB hash","author":"EESTABROO","date":"1999-03-26T00:53:04","distribution":"Passwd-DB","first":1,"maturity":"released","release":"Passwd-DB-1.00","status":"backpan","version":"1.00"},{"abstract":"Implementation of the Soundex Algorithm as Described by Knuth","author":"MARKM","date":"1999-03-26T00:19:53","distribution":"Text-Soundex","first":"","maturity":"released","release":"Text-Soundex-2.20","status":"backpan","version":"2.20"},{"abstract":"Perl module for manipulating the passwd and shadow files","author":"EESTABROO","date":"1999-03-25T22:17:40","distribution":"Passwd-Solaris","first":1,"maturity":"released","release":"Passwd-Solaris-0.60","status":"backpan","version":"0.60"},{"abstract":"script for generating site maps","author":"AWRIGLEY","date":"1999-03-25T17:59:52","distribution":"sitemapper","first":"","maturity":"released","release":"sitemapper-1.007","status":"backpan","version":"1.007"},{"abstract":"Structured text subclass","author":"PSHARPE","date":"1999-03-25T13:17:52","distribution":"TextStructured","first":1,"maturity":"released","release":"TextStructured-0.01","status":"backpan","version":"0.01"},{"abstract":"Processeur de templates contenant des expressions Perl (0.40)","author":"PVERD","date":"1999-03-25T12:26:30","distribution":"ParseTemplate","first":1,"maturity":"released","release":"ParseTemplate-0.31","status":"cpan","version":"0.31"},{"abstract":null,"author":"ANDYDUNC","date":"1999-03-25T12:08:04","distribution":"ORAC_WILL_BE_BACK","first":1,"maturity":"released","release":"ORAC_WILL_BE_BACK","status":"backpan","version":0},{"abstract":"Interface to pcap(3) LBL packet capture library","author":"TIMPOTTER","date":"1999-03-25T00:29:35","distribution":"Net-Pcap","first":"","maturity":"released","release":"Net-Pcap-0.03","status":"backpan","version":"0.03"},{"abstract":"Authenticate into a NIS+ domain","author":"VALERIE","date":"1999-03-25T00:09:58","distribution":"Apache-AuthenNISPlus","first":"","maturity":"released","release":"Apache-AuthenNISPlus-0.04","status":"cpan","version":"0.04"},{"abstract":"Authenticate into the NT and NIS+ domains","author":"VALERIE","date":"1999-03-25T00:08:26","distribution":"Apache-AuthenN2","first":"","maturity":"released","release":"Apache-AuthenN2-0.02","status":"cpan","version":"0.02"},{"abstract":"mod_perl NT Authentication module","author":"PARKER","date":"1999-03-24T21:37:40","distribution":"Apache-AuthenSmb","first":"","maturity":"released","release":"Apache-AuthenSmb-0.50","status":"backpan","version":"0.50"},{"abstract":"A generator for handlers suitable for use by Daily Update.","author":"DCOPPIT","date":"1999-03-24T21:16:32","distribution":"DailyUpdate","first":"","maturity":"released","release":"DailyUpdate-7.00","status":"backpan","version":"7.00"},{"abstract":"A perl module for parsing XML RDF documents","author":"LDACHARY","date":"1999-03-24T18:32:03","distribution":"XML-RDF","first":1,"maturity":"released","release":"XML-RDF-0.01","status":"backpan","version":"0.01"},{"abstract":"provide auto-configuration utilities","author":"KJALB","date":"1999-03-24T16:26:47","distribution":"TermReadKey","first":"","maturity":"released","release":"TermReadKey-2.13","status":"backpan","version":"2.13"},{"abstract":null,"author":"KJALB","date":"1999-03-24T16:17:40","distribution":"Devel-PPPort","first":1,"maturity":"released","release":"Devel-PPPort-1.0006","status":"cpan","version":"1.0006"},{"abstract":"module to truncate Japanese encoded text.","author":"AWRIGLEY","date":"1999-03-24T13:49:28","distribution":"HTML-Summary","first":"","maturity":"released","release":"HTML-Summary-0.014","status":"backpan","version":"0.014"},{"abstract":"Perl extension for writing Gimp Extensions/Plug-ins/Load & Save-Handlers","author":"MLEHMANN","date":"1999-03-24T12:36:58","distribution":"Gimp","first":"","maturity":"released","release":"Gimp-1.071a","status":"backpan","version":"1.071"},{"abstract":null,"author":"MJD","date":"1999-03-23T23:06:38","distribution":"y2k","first":1,"maturity":"released","release":"y2k","status":"backpan","version":0},{"abstract":"Get a stock quote from Yahoo!","author":"DJPADZ","date":"1999-03-23T20:50:57","distribution":"Finance-YahooQuote","first":"","maturity":"released","release":"Finance-YahooQuote-0.11","status":"cpan","version":"0.11"},{"abstract":"Get a stock quote from Yahoo!","author":"DJPADZ","date":"1999-03-23T17:22:56","distribution":"Finance-YahooQuote","first":"","maturity":"released","release":"Finance-YahooQuote-0.10","status":"cpan","version":"0.10"},{"abstract":"module to truncate Japanese encoded text.","author":"AWRIGLEY","date":"1999-03-23T16:54:16","distribution":"HTML-Summary","first":1,"maturity":"released","release":"HTML-Summary-0.013","status":"backpan","version":"0.013"},{"abstract":"Perl Extension For ObjectStore OODBMS","author":"JPRIT","date":"1999-03-23T14:49:02","distribution":"ObjStore","first":"","maturity":"released","release":"ObjStore-1.55","status":"cpan","version":"1.55"},{"abstract":"A perl module for parsing XML documents","author":"ASANDSTRM","date":"1999-03-23T12:54:39","distribution":"XML-Parser","first":1,"maturity":"released","release":"XML-Parser-2.21-bin-1-MacOS","status":"backpan","version":"2.21"},{"abstract":"Declaratively Expressed Command-Line Arguments via Regular Expressions","author":"DCONWAY","date":"1999-03-23T05:41:30","distribution":"Getopt-Declare","first":"","maturity":"released","release":"Getopt-Declare-1.07","status":"backpan","version":"1.07"},{"abstract":null,"author":"DOUGL","date":"1999-03-23T02:06:25","distribution":"PerlCRT","first":"","maturity":"released","release":"PerlCRT-1.04-bin-1-x86-VC","status":"cpan","version":"1.04"},{"abstract":null,"author":"DOUGL","date":"1999-03-23T02:06:19","distribution":"PerlCRT","first":"","maturity":"released","release":"PerlCRT-1.04-bin-1-debug-x86-VC","status":"cpan","version":"1.04"},{"abstract":null,"author":"DOUGL","date":"1999-03-23T02:06:16","distribution":"PerlCRT","first":"","maturity":"released","release":"PerlCRT-1.04-bin-1-debug-Alpha-VC","status":"cpan","version":"1.04"},{"abstract":null,"author":"DOUGL","date":"1999-03-23T02:06:10","distribution":"PerlCRT","first":"","maturity":"released","release":"PerlCRT-1.04-bin-1-Alpha-VC","status":"cpan","version":"1.04"},{"abstract":"Get a stock quote from Yahoo!","author":"DJPADZ","date":"1999-03-22T19:46:15","distribution":"Finance-YahooQuote","first":"","maturity":"released","release":"Finance-YahooQuote-0.09","status":"cpan","version":"0.09"},{"abstract":null,"author":"ANDYDUNC","date":"1999-03-22T18:27:45","distribution":"ORAC-DBA","first":"","maturity":"released","release":"ORAC-DBA-0.03","status":"backpan","version":"0.03"},{"abstract":"Perl Extension For ObjectStore OODBMS","author":"JPRIT","date":"1999-03-22T17:07:23","distribution":"ObjStore","first":"","maturity":"released","release":"ObjStore-1.54","status":"cpan","version":"1.54"},{"abstract":"Merge multiple data sources into a hash","author":"RRA","date":"1999-03-22T15:42:50","distribution":"ShadowHash","first":1,"maturity":"released","release":"ShadowHash-0.03","status":"backpan","version":"0.03"},{"abstract":"parse text into an array of tokens or array of arrays","author":"HALPOM","date":"1999-03-22T10:44:14","distribution":"Text-ParseWords","first":1,"maturity":"released","release":"Text-ParseWords-3.1","status":"cpan","version":"3.1"},{"abstract":"Ties a Tk::Menubutton widget to a hash object thingy","author":"ZENIN","date":"1999-03-22T08:47:52","distribution":"Tk-MenuHash","first":"","maturity":"released","release":"Tk-MenuHash-1.12","status":"latest","version":"1.12"},{"abstract":null,"author":"SUMMER","date":"1999-03-22T08:14:42","distribution":"pixmaped","first":"","maturity":"released","release":"pixmaped-1.30","status":"backpan","version":"1.30"},{"abstract":"Perl module to download and save information from the Web","author":"IKLUFT","date":"1999-03-22T07:15:51","distribution":"WebFetch","first":"","maturity":"released","release":"WebFetch-0.03","status":"backpan","version":"0.03"},{"abstract":"A perl module for parsing XML documents","author":"COOPERCL","date":"1999-03-21T22:58:12","distribution":"XML-Parser","first":"","maturity":"released","release":"XML-Parser-2.21","status":"cpan","version":"2.21"},{"abstract":"Perl extension to access the unix process table","author":"DURIST","date":"1999-03-21T16:07:46","distribution":"Proc-ProcessTable","first":"","maturity":"released","release":"Proc-ProcessTable-0.12","status":"backpan","version":"0.12"},{"abstract":null,"author":"HORROCKS","date":"1999-03-21T10:51:03","distribution":"SpeedyCGI","first":1,"maturity":"released","release":"SpeedyCGI-1.3","status":"backpan","version":"1.3"},{"abstract":"Suite of modules to themeify a website","author":"JSMITH","date":"1999-03-21T07:16:27","distribution":"CGI-WeT","first":"","maturity":"released","release":"CGI-WeT-0.6.3","status":"backpan","version":"v0.6.3"},{"abstract":"Simple access to Mac::OSA","author":"CNANDOR","date":"1999-03-20T19:53:36","distribution":"Mac-OSA-Simple","first":"","maturity":"released","release":"Mac-OSA-Simple-0.51","status":"backpan","version":"0.51"},{"abstract":"Low-level support for Perl embedded in GNU Emacs","author":"JTOBEY","date":"1999-03-20T19:30:58","distribution":"Emacs-Lisp","first":"","maturity":"released","release":"Emacs-Lisp-0.89","status":"backpan","version":"0.89"},{"abstract":"Get a stock quote from Yahoo!","author":"DJPADZ","date":"1999-03-20T16:46:40","distribution":"Finance-YahooQuote","first":"","maturity":"released","release":"Finance-YahooQuote-0.08","status":"cpan","version":"0.08"},{"abstract":"Tk interface for bicycle power-output calculator","author":"SREZIC","date":"1999-03-20T14:44:29","distribution":"BikePower","first":"","maturity":"released","release":"BikePower-0.31","status":"backpan","version":"0.31"},{"abstract":"a date/time widget for perl/Tk","author":"SREZIC","date":"1999-03-20T14:17:19","distribution":"Tk-Date","first":"","maturity":"released","release":"Tk-Date-0.27","status":"backpan","version":"0.27"},{"abstract":"libwww-perl cookbook","author":"GAAS","date":"1999-03-20T07:52:48","distribution":"libwww-perl","first":"","maturity":"released","release":"libwww-perl-5.42","status":"backpan","version":"5.42"},{"abstract":"Uniform Resource Identifiers (absolute and relative)","author":"GAAS","date":"1999-03-20T07:52:47","distribution":"URI","first":"","maturity":"released","release":"URI-1.01","status":"backpan","version":"1.01"},{"abstract":"Low-level support for Perl embedded in GNU Emacs","author":"JTOBEY","date":"1999-03-20T03:54:33","distribution":"Emacs-Lisp","first":"","maturity":"released","release":"Emacs-Lisp-0.88","status":"backpan","version":"0.88"},{"abstract":null,"author":"JHOWELL","date":"1999-03-20T02:42:11","distribution":"FAQ-OMatic","first":"","maturity":"released","release":"FAQ-OMatic-2.621","status":"cpan","version":"2.621"},{"abstract":null,"author":"JHOWELL","date":"1999-03-20T02:13:20","distribution":"FAQ-OMatic","first":"","maturity":"released","release":"FAQ-OMatic-2.620","status":"backpan","version":"2.620"},{"abstract":"A perl module for querying XML tree structures with XQL","author":"ENNO","date":"1999-03-19T23:34:54","distribution":"XML-XQL","first":"","maturity":"released","release":"XML-XQL-0.60","status":"backpan","version":"0.60"},{"abstract":"Perl extension for statvfs().","author":"IGUTHRIE","date":"1999-03-19T20:53:10","distribution":"Filesys-Statvfs_Df","first":"","maturity":"released","release":"Filesys-Statvfs_Df-0.55","status":"backpan","version":"0.55"},{"abstract":"base class for objects that can read and write text lines","author":"JV","date":"1999-03-19T19:19:27","distribution":"Text-Filter","first":"","maturity":"released","release":"Text-Filter-1.6","status":"backpan","version":"1.6"},{"abstract":"Low-level support for Perl embedded in GNU Emacs","author":"JTOBEY","date":"1999-03-19T16:44:13","distribution":"Emacs-Lisp","first":"","maturity":"released","release":"Emacs-Lisp-0.87","status":"backpan","version":"0.87"},{"abstract":"Entry widget with history capability","author":"SREZIC","date":"1999-03-19T08:23:09","distribution":"Tk-HistEntry","first":"","maturity":"released","release":"Tk-HistEntry-0.31","status":"backpan","version":"0.31"},{"abstract":null,"author":"SUMMER","date":"1999-03-19T08:15:36","distribution":"pixmaped","first":"","maturity":"released","release":"pixmaped-1.19","status":"backpan","version":"1.19"},{"abstract":null,"author":"SUMMER","date":"1999-03-19T08:14:05","distribution":"petris","first":"","maturity":"released","release":"petris-1.07","status":"backpan","version":"1.07"},{"abstract":null,"author":"SUMMER","date":"1999-03-19T08:14:03","distribution":"snake","first":"","maturity":"released","release":"snake-1.06","status":"backpan","version":"1.06"},{"abstract":"comma-separated values manipulation routines","author":"CNANDOR","date":"1999-03-19T05:08:40","distribution":"Text-CSV_XS","first":"","maturity":"released","release":"Text-CSV_XS-0.17-bin-1-Mac","status":"backpan","version":"0.17"},{"abstract":"SQL parsing and processing engine","author":"CNANDOR","date":"1999-03-19T05:08:39","distribution":"SQL-Stmnt","first":"","maturity":"released","release":"SQL-Stmnt-0.1011-bin-1-Mac","status":"backpan","version":"0.1011"},{"abstract":"Encoding and decoding of quoted-printable strings","author":"CNANDOR","date":"1999-03-19T05:07:07","distribution":"MIME-Base64","first":"","maturity":"released","release":"MIME-Base64-2.11-bin-1-Mac","status":"backpan","version":"2.11"},{"abstract":"Perl interface to the MD5 Algorithm","author":"CNANDOR","date":"1999-03-19T05:05:36","distribution":"Digest-MD5","first":"","maturity":"released","release":"Digest-MD5-2.05-bin-1-Mac","status":"backpan","version":"2.05"},{"abstract":"Perl module for basic IMAP server administration","author":"EESTABROO","date":"1999-03-18T22:48:44","distribution":"IMAP-Admin","first":"","maturity":"released","release":"IMAP-Admin-0.8.2","status":"backpan","version":"v0.8.2"},{"abstract":null,"author":"CKAISER","date":"1999-03-18T21:25:48","distribution":"httpi","first":"","maturity":"released","release":"httpi-0.7","status":"backpan","version":"0.7"},{"abstract":null,"author":"SUMMER","date":"1999-03-18T08:22:53","distribution":"pixmaped","first":"","maturity":"released","release":"pixmaped-1.17","status":"backpan","version":"1.17"},{"abstract":"LDAP Uniform Resource Locators","author":"GBARR","date":"1999-03-18T02:58:45","distribution":"perl-ldap","first":"","maturity":"released","release":"perl-ldap-0.10","status":"backpan","version":"0.10"},{"abstract":"Get a stock quote from Yahoo!","author":"DJPADZ","date":"1999-03-18T00:34:03","distribution":"Finance-YahooQuote","first":"","maturity":"released","release":"Finance-YahooQuote-0.07","status":"cpan","version":"0.07"},{"abstract":"tee source filter","author":"PMQS","date":"1999-03-17T22:00:20","distribution":"Filter","first":"","maturity":"released","release":"Filter-1.16","status":"cpan","version":"1.16"},{"abstract":null,"author":"PMQS","date":"1999-03-17T21:58:48","distribution":"Compress-Zlib","first":"","maturity":"released","release":"Compress-Zlib-1.03","status":"cpan","version":"1.03"},{"abstract":"A bundle to install the DBD::CSV driver","author":"JWIED","date":"1999-03-17T21:48:14","distribution":"DBD-CSV","first":"","maturity":"released","release":"DBD-CSV-0.1020","status":"backpan","version":"0.1020"},{"abstract":"interpolates script options from files into @ARGV","author":"JSTENZEL","date":"1999-03-17T21:18:03","distribution":"Getopt-ArgvFile","first":1,"maturity":"released","release":"Getopt-ArgvFile-1.0","status":"cpan","version":"1.0"},{"abstract":"Entry widget with history capability","author":"SREZIC","date":"1999-03-17T19:09:57","distribution":"Tk-HistEntry","first":"","maturity":"released","release":"Tk-HistEntry-0.30","status":"backpan","version":"0.30"},{"abstract":"A perl module for building DOM Level 1 compliant document structures","author":"ENNO","date":"1999-03-17T16:16:31","distribution":"XML-DOM","first":"","maturity":"released","release":"XML-DOM-1.18","status":"backpan","version":"1.18"},{"abstract":"Simple Network Management Protocol version-1","author":"DTOWN","date":"1999-03-17T13:51:17","distribution":"Net-SNMP","first":"","maturity":"released","release":"Net-SNMP-1.30","status":"backpan","version":"1.30"},{"abstract":null,"author":"JPRIT","date":"1999-03-16T23:52:40","distribution":"Event-tcpserv","first":"","maturity":"released","release":"Event-tcpserv-0.03","status":"backpan","version":"0.03"},{"abstract":"Perl/Tk script to provide a graphical user interface for testing Perl/Tk commands and scripts.","author":"NI-S","date":"1999-03-16T22:13:10","distribution":"Tk","first":"","maturity":"released","release":"Tk800.013","status":"backpan","version":"800.013"},{"abstract":"Perl interface to PARI.","author":"ILYAZ","date":"1999-03-16T18:59:00","distribution":"Math-Pari","first":"","maturity":"released","release":"Math-Pari-2.001401","status":"cpan","version":"2.001401"},{"abstract":"Resources catalog management and display","author":"LDACHARY","date":"1999-03-16T16:11:23","distribution":"Catalog","first":"","maturity":"released","release":"Catalog-0.4","status":"backpan","version":"0.4"},{"abstract":"framework for software localization","author":"SBURKE","date":"1999-03-16T05:22:44","distribution":"Locale-Maketext","first":1,"maturity":"released","release":"Locale-Maketext-0.17","status":"backpan","version":"0.17"},{"abstract":"High resolution ualarm, usleep, and gettimeofday","author":"DEWEG","date":"1999-03-16T02:44:02","distribution":"Time-HiRes","first":"","maturity":"released","release":"Time-HiRes-01.20","status":"cpan","version":"01.20"},{"abstract":"Object Persistence with Data::Dumper.","author":"VIPUL","date":"1999-03-15T21:48:31","distribution":"Object-Persistence","first":"","maturity":"released","release":"Object-Persistence-0.33","status":"backpan","version":"0.33"},{"abstract":"Make temporary filename from template","author":"TGUMMELS","date":"1999-03-15T21:07:43","distribution":"File-MkTemp","first":"","maturity":"released","release":"File-MkTemp-1.0.1","status":"cpan","version":"v1.0.1"},{"abstract":"Event loop processing","author":"JPRIT","date":"1999-03-15T15:44:57","distribution":"Event","first":"","maturity":"released","release":"Event-0.32","status":"backpan","version":"0.32"},{"abstract":"Perl interface to the MD5 Algorithm","author":"GAAS","date":"1999-03-15T10:58:32","distribution":"Digest-MD5","first":"","maturity":"released","release":"Digest-MD5-2.05","status":"backpan","version":"2.05"},{"abstract":null,"author":"SUMMER","date":"1999-03-15T08:24:25","distribution":"petris","first":"","maturity":"released","release":"petris-1.06","status":"backpan","version":"1.06"},{"abstract":"Perl interface to PARI.","author":"ILYAZ","date":"1999-03-15T06:53:00","distribution":"Math-Pari","first":"","maturity":"released","release":"Math-Pari-2.001400","status":"cpan","version":"2.001400"},{"abstract":"Perl extension for writing Gimp Extensions/Plug-ins/Load & Save-Handlers","author":"MLEHMANN","date":"1999-03-15T00:29:37","distribution":"Gimp","first":"","maturity":"released","release":"Gimp-1.07","status":"backpan","version":"1.07"},{"abstract":"bicycle power-output calculator with command-line and Tk interface","author":"SREZIC","date":"1999-03-14T23:41:22","distribution":"BikePower","first":"","maturity":"released","release":"BikePower-0.30","status":"backpan","version":"0.30"},{"abstract":"Perl interface cyclic redundency check generation","author":"SOENKE","date":"1999-03-14T20:11:36","distribution":"String-CRC32","first":"","maturity":"released","release":"String-CRC32-0.9","status":"backpan","version":"0.9"},{"abstract":"Perl5 access to Berkeley DB version 1.x","author":"PMQS","date":"1999-03-14T14:38:30","distribution":"DB_File","first":"","maturity":"released","release":"DB_File-1.65","status":"cpan","version":"1.65"},{"abstract":"Convert an XML file into a suite of CGI forms.","author":"RSAVAGE","date":"1999-03-14T02:11:52","distribution":"CGI-Formalware","first":1,"maturity":"released","release":"CGI-Formalware-1.03","status":"backpan","version":"1.03"},{"abstract":"a series of charting modules","author":"NINJAZ","date":"1999-03-13T06:37:09","distribution":"Chart","first":"","maturity":"released","release":"Chart-0.99b","status":"cpan","version":"0.99"},{"abstract":"Perl extension to authenticate against an SMB server","author":"PMKANE","date":"1999-03-13T04:24:29","distribution":"Authen-Smb","first":"","maturity":"released","release":"Authen-Smb-0.6","status":"cpan","version":"0.6"},{"abstract":"Perl extension to authenticate against an SMB server","author":"PMKANE","date":"1999-03-13T04:16:55","distribution":"Authen-Smb","first":"","maturity":"released","release":"Authen-Smb-0.5","status":"cpan","version":"0.5"},{"abstract":"context-sensitive help with perl/Tk","author":"SREZIC","date":"1999-03-13T03:46:42","distribution":"Tk-ContextHelp","first":1,"maturity":"released","release":"Tk-ContextHelp-0.06","status":"backpan","version":"0.06"},{"abstract":"Perl module for basic IMAP server administration","author":"EESTABROO","date":"1999-03-13T01:17:27","distribution":"IMAP-Admin","first":"","maturity":"released","release":"IMAP-Admin-0.8.1","status":"backpan","version":"v0.8.1"},{"abstract":"Perl extension for tie'ing a filehandle to Syslog","author":"BROCSEIB","date":"1999-03-12T23:57:33","distribution":"Tie-Syslog","first":1,"maturity":"released","release":"Tie-Syslog-1.01","status":"backpan","version":"1.01"},{"abstract":"perl replacement for uudecode","author":"ANDK","date":"1999-03-12T21:32:38","distribution":"Convert-UU","first":"","maturity":"released","release":"Convert-UU-0.40","status":"backpan","version":"0.40"},{"abstract":"module for generating a summary from a web page.","author":"AWRIGLEY","date":"1999-03-12T21:02:28","distribution":"HTML-Summary","first":1,"maturity":"released","release":"HTML-Summary-0.012","status":"backpan","version":"0.012"},{"abstract":"Perl extension for writing Gimp Extensions/Plug-ins/Load & Save-Handlers","author":"MLEHMANN","date":"1999-03-12T20:47:17","distribution":"Gimp","first":"","maturity":"released","release":"Gimp-1.061","status":"backpan","version":"1.061"},{"abstract":"create Cache Digests from lists of URLs","author":"MHAMILTON","date":"1999-03-12T19:09:12","distribution":"WebCache-Digest","first":1,"maturity":"released","release":"WebCache-Digest-1.00","status":"latest","version":"1.00"},{"abstract":"Simple access to Mac::OSA","author":"CNANDOR","date":"1999-03-12T15:08:00","distribution":"Mac-OSA-Simple","first":"","maturity":"released","release":"Mac-OSA-Simple-0.50","status":"backpan","version":"0.50"},{"abstract":"versatile text pre-processor","author":"DDUMONT","date":"1999-03-12T14:57:23","distribution":"Text-Vpp","first":"","maturity":"released","release":"Text-Vpp-1.11","status":"backpan","version":"1.11"},{"abstract":"Switch to ANSI C++ exceptions","author":"JPRIT","date":"1999-03-12T14:57:20","distribution":"Exception-Cxx","first":1,"maturity":"released","release":"Exception-Cxx-1.00","status":"cpan","version":"1.00"},{"abstract":"Truetype Collection class","author":"MHOSKEN","date":"1999-03-12T11:53:24","distribution":"Font-TTF","first":"","maturity":"released","release":"Font-TTF-0.04","status":"backpan","version":"0.04"},{"abstract":"Perl extension for accessing protected password database","author":"PAULG","date":"1999-03-12T06:39:27","distribution":"Authen-Prot","first":"","maturity":"released","release":"Authen-Prot-1.08","status":"latest","version":"1.08"},{"abstract":"Perl module to rotate logfiles.","author":"PAULG","date":"1999-03-12T06:37:53","distribution":"Logfile-Rotate","first":"","maturity":"released","release":"Logfile-Rotate-1.03","status":"cpan","version":"1.03"},{"abstract":"Frequently-Asked Questions about btparse and Text::BibTeX","author":"GWARD","date":"1999-03-12T03:27:55","distribution":"Text-BibTeX","first":"","maturity":"released","release":"Text-BibTeX-0.30","status":"cpan","version":"0.30"},{"abstract":"input/parsing functions in btparse library","author":"GWARD","date":"1999-03-12T03:26:20","distribution":"btparse","first":"","maturity":"released","release":"btparse-0.30","status":"cpan","version":"0.30"},{"abstract":null,"author":"MSCHWARTZ","date":"1999-03-12T01:04:34","distribution":"Document-Info","first":1,"maturity":"released","release":"Document-Info-0.01","status":"latest","version":"0.01"},{"abstract":"Perl interface to VMS device system calls ($GETDVI and friends)","author":"DSUGAL","date":"1999-03-11T22:42:19","distribution":"VMS-Device","first":"","maturity":"released","release":"VMS-Device-0_06","status":"cpan","version":"0_06"},{"abstract":"Make temporary filename from template","author":"TGUMMELS","date":"1999-03-11T20:38:36","distribution":"File-MkTemp","first":1,"maturity":"released","release":"File-MkTemp-1.0.0","status":"cpan","version":"v1.0.0"},{"abstract":null,"author":"PVERD","date":"1999-03-11T13:57:20","distribution":"RTF-Parser","first":"","maturity":"released","release":"RTF-Parser-1.06","status":"cpan","version":"1.06"},{"abstract":null,"author":"SUMMER","date":"1999-03-11T08:23:27","distribution":"pixmaped","first":"","maturity":"released","release":"pixmaped-1.15","status":"backpan","version":"1.15"},{"abstract":"Perl module to fix the case of people's names.","author":"SUMMER","date":"1999-03-11T08:21:55","distribution":"NameCase","first":"","maturity":"released","release":"NameCase.pm-1.02","status":"backpan","version":"1.02"},{"abstract":"Choose a color","author":"KJALB","date":"1999-03-11T01:30:23","distribution":"Gtk","first":"","maturity":"released","release":"Gtk-0.5120","status":"cpan","version":"0.5120"},{"abstract":"Base for deriving evalution objects for SQL::Statement","author":"JWIED","date":"1999-03-10T22:42:53","distribution":"SQL-Statement","first":"","maturity":"released","release":"SQL-Statement-0.1011","status":"cpan","version":"0.1011"},{"abstract":"Oracle database driver for the DBI module","author":"TIMB","date":"1999-03-10T20:57:21","distribution":"DBD-Oracle","first":"","maturity":"released","release":"DBD-Oracle-0.60","status":"backpan","version":"0.60"},{"abstract":"read the dimensions of an image in several popular formats","author":"RJRAY","date":"1999-03-10T20:28:42","distribution":"Image-Size","first":"","maturity":"released","release":"Image-Size-2.901","status":"backpan","version":"2.901"},{"abstract":"perl replacement for uudecode","author":"ANDK","date":"1999-03-10T18:55:11","distribution":"Convert-UU","first":"","maturity":"released","release":"Convert-UU-0.30","status":"backpan","version":"0.30"},{"abstract":"Perl extension for generating and using LALR parsers.","author":"FDESAR","date":"1999-03-10T16:53:05","distribution":"Parse-Yapp","first":"","maturity":"released","release":"Parse-Yapp-0.22","status":"cpan","version":"0.22"},{"abstract":"Perl Extension to Implement Fat-Node Trees","author":"JPRIT","date":"1999-03-10T16:10:50","distribution":"Tree-Fat","first":"","maturity":"released","release":"Tree-Fat-1.111","status":"latest","version":"1.111"},{"abstract":"Truetype Collection class","author":"MHOSKEN","date":"1999-03-10T11:19:33","distribution":"Font-TTF","first":1,"maturity":"released","release":"Font-TTF-0.03","status":"backpan","version":"0.03"},{"abstract":"read the dimensions of an image in several popular formats","author":"RJRAY","date":"1999-03-10T08:37:24","distribution":"Image-Size","first":"","maturity":"released","release":"Image-Size-2.10","status":"backpan","version":"2.10"},{"abstract":null,"author":"SUMMER","date":"1999-03-10T08:20:45","distribution":"pixmaped","first":"","maturity":"released","release":"pixmaped-1.14","status":"backpan","version":"1.14"},{"abstract":"Perl/Tk module for message and button dialogue boxes.","author":"SUMMER","date":"1999-03-10T08:20:44","distribution":"MesgBox","first":1,"maturity":"released","release":"MesgBox.pm-1.05","status":"backpan","version":"1.05"},{"abstract":"Perl module providing 3-value logic versions of \"and\", \"or\", \"xor\" and \"not\".","author":"SUMMER","date":"1999-03-10T08:20:43","distribution":"Logic","first":"","maturity":"released","release":"Logic3.pm-1.03","status":"backpan","version":"3."},{"abstract":"Perl/Tk module providing a Colour selection dialogue box.","author":"SUMMER","date":"1999-03-10T08:20:41","distribution":"ColourChooser","first":"","maturity":"released","release":"ColourChooser.pm-1.11","status":"backpan","version":"1.11"},{"abstract":"Low-level support for Perl embedded in GNU Emacs","author":"JTOBEY","date":"1999-03-10T06:53:16","distribution":"Emacs-Lisp","first":"","maturity":"released","release":"Emacs-Lisp-0.84","status":"backpan","version":"0.84"},{"abstract":"Compute `intelligent' differences between two files / lists","author":"MJD","date":"1999-03-10T06:35:08","distribution":"Algorithm-Diff","first":"","maturity":"released","release":"Algorithm-Diff-0.59","status":"backpan","version":"0.59"},{"abstract":"Perl Extension to Implement Fat-Node Trees","author":"JPRIT","date":"1999-03-09T23:01:19","distribution":"Tree-Fat","first":"","maturity":"released","release":"Tree-Fat-1.11","status":"backpan","version":"1.11"},{"abstract":"Simple access to Mac::OSA","author":"CNANDOR","date":"1999-03-09T22:44:38","distribution":"Mac-OSA-Simple","first":"","maturity":"released","release":"Mac-OSA-Simple-0.10","status":"backpan","version":"0.10"},{"abstract":null,"author":"JPRIT","date":"1999-03-09T14:30:17","distribution":"Event-tcpserv","first":"","maturity":"released","release":"Event-tcpserv-0.02","status":"backpan","version":"0.02"},{"abstract":"Event loop processing","author":"JPRIT","date":"1999-03-09T14:25:25","distribution":"Event","first":"","maturity":"released","release":"Event-0.31","status":"backpan","version":"0.31"},{"abstract":"efficient base class implementing bit vectors.","author":"ASANDSTRM","date":"1999-03-09T09:53:27","distribution":"Bit-Vector","first":1,"maturity":"released","release":"Bit-Vector-5.6-bin-2-MacOS","status":"cpan","version":"5.6"},{"abstract":"Support for Perl embedded in GNU Emacs","author":"JTOBEY","date":"1999-03-09T06:44:59","distribution":"Emacs-Lisp","first":"","maturity":"released","release":"Emacs-Lisp-0.83","status":"backpan","version":"0.83"},{"abstract":"An object that may be used to construct a block of text in PostScript.","author":"SHAWNPW","date":"1999-03-09T03:24:31","distribution":"PostScript","first":"","maturity":"released","release":"PostScript-0.05","status":"cpan","version":"0.05"},{"abstract":"Generate CODE 128 bar codes","author":"WRW","date":"1999-03-09T02:39:17","distribution":"Barcode-Code128","first":1,"maturity":"released","release":"Barcode-Code128-1.0","status":"backpan","version":"1.0"},{"abstract":"Perl extension for formatting numbers","author":"WRW","date":"1999-03-09T02:39:03","distribution":"Number-Format","first":"","maturity":"released","release":"Number-Format-1.41","status":"backpan","version":"1.41"},{"abstract":"Compute `intelligent' differences between two files / lists","author":"MJD","date":"1999-03-08T19:30:29","distribution":"Algorithm-Diff","first":"","maturity":"released","release":"Algorithm-Diff-0.58","status":"backpan","version":"0.58"},{"abstract":"Fast CGI module","author":"SKIMO","date":"1999-03-08T17:04:02","distribution":"FCGI","first":"","maturity":"released","release":"FCGI-0.45","status":"backpan","version":"0.45"},{"abstract":"a class to manipulate Gedcom genealogy files","author":"PJCJ","date":"1999-03-08T16:21:41","distribution":"Gedcom","first":1,"maturity":"released","release":"Gedcom-1.00","status":"backpan","version":"1.00"},{"abstract":"PDF Dictionaries and Streams. Inherits from PDF::Objind","author":"MHOSKEN","date":"1999-03-08T14:57:14","distribution":"pdf","first":1,"maturity":"released","release":"pdf-0.01","status":"backpan","version":"0.01"},{"abstract":"Utility functions to save fingers","author":"MHOSKEN","date":"1999-03-08T14:55:41","distribution":"TTF","first":1,"maturity":"released","release":"TTF-0.02","status":"backpan","version":"0.02"},{"abstract":"efficient base class implementing bit vectors.","author":"ASANDSTRM","date":"1999-03-08T10:03:04","distribution":"Bit-Vector","first":1,"maturity":"released","release":"Bit-Vector-5.6-bin-1-MacOS","status":"backpan","version":"5.6"},{"abstract":"Perl/Tk module for message and button dialogue boxes.","author":"SUMMER","date":"1999-03-08T08:24:10","distribution":"pixmaped","first":"","maturity":"released","release":"pixmaped-1.10","status":"backpan","version":"1.10"},{"abstract":"Perl/Tk module providing a Colour selection dialogue box.","author":"SUMMER","date":"1999-03-08T08:22:34","distribution":"ColourChooser","first":"","maturity":"released","release":"ColourChooser-1.10","status":"backpan","version":"1.10"},{"abstract":null,"author":"KJALB","date":"1999-03-08T02:57:02","distribution":"Term-Info","first":1,"maturity":"released","release":"Term-Info-1.1","status":"latest","version":"1.1"},{"abstract":null,"author":"KJALB","date":"1999-03-08T02:57:01","distribution":"Devel-PPPort","first":1,"maturity":"released","release":"Devel-PPPort-1.0005","status":"cpan","version":"1.0005"},{"abstract":"Expand template text with embedded Perl","author":"MJD","date":"1999-03-08T02:17:50","distribution":"Text-Template","first":"","maturity":"released","release":"Text-Template-1.20","status":"backpan","version":"1.20"},{"abstract":"a pure Perl Infocom (z-code) game interpreter","author":"EDMONSON","date":"1999-03-08T02:01:01","distribution":"Games-Rezrov","first":"","maturity":"released","release":"Games-Rezrov-0.16","status":"cpan","version":"0.16"},{"abstract":"Perform text substitutions on an HTML template","author":"KAELIN","date":"1999-03-07T23:57:27","distribution":"HTML-Subtext","first":1,"maturity":"released","release":"HTML-Subtext-1.03","status":"latest","version":"1.03"},{"abstract":"An improved text widget for perl/tk","author":"ALEXIOB","date":"1999-03-07T23:12:07","distribution":"Tk-Text-SuperText","first":"","maturity":"released","release":"Tk-Text-SuperText-0.9.2","status":"backpan","version":"v0.9.2"},{"abstract":"Interface to Bzip2 compression library","author":"AZEMGI","date":"1999-03-07T20:24:48","distribution":"Compress-Bzip2","first":1,"maturity":"released","release":"Compress-Bzip2-1.00","status":"backpan","version":"1.00"},{"abstract":"functions for dealing with RFC1766-style language tags","author":"SBURKE","date":"1999-03-07T18:51:20","distribution":"I18N-LangTags","first":"","maturity":"released","release":"I18N-LangTags-0.12","status":"backpan","version":"0.12"},{"abstract":"base class for objects that can read and write text lines","author":"JV","date":"1999-03-07T15:44:25","distribution":"Text-Filter","first":"","maturity":"released","release":"Text-Filter-1.5","status":"backpan","version":"1.5"},{"abstract":"make sample pages from PostScript fonts","author":"JV","date":"1999-03-07T15:41:18","distribution":"PostScript-Font","first":"","maturity":"released","release":"PostScript-Font-1.0","status":"backpan","version":"1.0"},{"abstract":"link identical files in source trees","author":"JV","date":"1999-03-07T15:38:16","distribution":"lntree","first":"","maturity":"released","release":"lntree-1.9","status":"backpan","version":"1.9"},{"abstract":"Support for Perl embedded in GNU Emacs","author":"JTOBEY","date":"1999-03-07T06:23:20","distribution":"Emacs-Lisp","first":"","maturity":"released","release":"Emacs-Lisp-0.80","status":"backpan","version":"0.80"},{"abstract":"Makes an object be the database connection","author":"MSCHWERN","date":"1999-03-07T04:07:36","distribution":"Ima-DBI","first":1,"maturity":"released","release":"Ima-DBI-0.01","status":"backpan","version":"0.01"},{"abstract":"An object that may be used to construct a block of text in PostScript.","author":"SHAWNPW","date":"1999-03-07T03:28:22","distribution":"PostScript","first":"","maturity":"released","release":"PostScript-0.04","status":"backpan","version":"0.04"},{"abstract":"functions for dealing with RFC1766-style language tags","author":"SBURKE","date":"1999-03-07T02:52:09","distribution":"I18N-LangTags","first":"","maturity":"released","release":"I18N-LangTags-0.11","status":"backpan","version":"0.11"},{"abstract":"Perl extension to access the unix process table","author":"DURIST","date":"1999-03-07T00:16:52","distribution":"Proc-ProcessTable","first":"","maturity":"released","release":"Proc-ProcessTable-0.11","status":"backpan","version":"0.11"},{"abstract":"Suite of modules to themeify a website","author":"JSMITH","date":"1999-03-06T20:08:05","distribution":"CGI-WeT","first":"","maturity":"released","release":"CGI-WeT-0.6.2","status":"backpan","version":"v0.6.2"},{"abstract":"Perl extension for writing Gimp Extensions/Plug-ins/Load & Save-Handlers","author":"MLEHMANN","date":"1999-03-06T20:03:33","distribution":"Gimp","first":"","maturity":"released","release":"Gimp-1.06","status":"backpan","version":"1.06"},{"abstract":"query, download and build perl modules from CPAN sites","author":"ANDK","date":"1999-03-06T19:34:54","distribution":"CPAN","first":"","maturity":"released","release":"CPAN-1.48","status":"backpan","version":"1.48"},{"abstract":"Suite of modules to themeify a website","author":"JSMITH","date":"1999-03-06T19:04:44","distribution":"CGI-WeT","first":1,"maturity":"released","release":"CGI-WeT-0.6.1","status":"backpan","version":"v0.6.1"},{"abstract":"link identical files in source trees","author":"JV","date":"1999-03-06T10:05:05","distribution":"lntree","first":"","maturity":"released","release":"lntree-1.8","status":"backpan","version":"1.8"},{"abstract":"Perl interface to the MD5 Algorithm","author":"GAAS","date":"1999-03-05T21:17:35","distribution":"Digest-MD5","first":"","maturity":"released","release":"Digest-MD5-2.04","status":"backpan","version":"2.04"},{"abstract":"base class for creating POD filters and translators","author":"BRADAPP","date":"1999-03-05T21:00:59","distribution":"PodParser","first":"","maturity":"released","release":"PodParser-1.08","status":"cpan","version":"1.08"},{"abstract":"alife simulator for Conway/Patterson/Beeler worms, etc.","author":"SBURKE","date":"1999-03-05T20:01:57","distribution":"Games-Worms","first":"","maturity":"released","release":"Games-Worms-0.61","status":"backpan","version":"0.61"},{"abstract":"class encapsulating US-style amortization","author":"SBURKE","date":"1999-03-05T19:48:18","distribution":"Business-US_Amort","first":1,"maturity":"released","release":"Business-US_Amort-0.04","status":"backpan","version":"0.04"},{"abstract":"PCDOCS/Fulcrum SearchServer database driver for the DBI module","author":"SHARI","date":"1999-03-05T09:10:01","distribution":"DBD-SearchServer","first":1,"maturity":"released","release":"DBD-SearchServer-0.21","status":"latest","version":"0.21"},{"abstract":"v.0.22 General purpose text/data merging methods in Perl.","author":"SHARRIS","date":"1999-03-05T08:48:51","distribution":"Text-Merge","first":"","maturity":"released","release":"Text-Merge-0.22","status":"backpan","version":"0.22"},{"abstract":"Perl module for basic IMAP server administration","author":"EESTABROO","date":"1999-03-05T04:03:56","distribution":"IMAP-Admin","first":1,"maturity":"released","release":"IMAP-Admin-0.7.0","status":"backpan","version":"v0.7.0"},{"abstract":"converts a collection of POD pages to HTML format.","author":"GBARR","date":"1999-03-05T02:22:53","distribution":"perl","first":"","maturity":"developer","release":"perl5.005_03-MAINT_TRIAL_6","status":"backpan","version":"5.005_03"},{"abstract":"Perl extension to authenticate against an SMB server","author":"PMKANE","date":"1999-03-05T00:33:53","distribution":"Authen-Smb","first":"","maturity":"released","release":"Authen-Smb-0.4","status":"cpan","version":"0.4"},{"abstract":"A modern soundex. Phonetic encoding of words.","author":"MSCHWERN","date":"1999-03-04T23:51:37","distribution":"Text-Metaphone","first":"","maturity":"released","release":"Text-Metaphone-1.96","status":"backpan","version":"1.96"},{"abstract":"comma-separated values manipulation routines","author":"JWIED","date":"1999-03-04T19:35:08","distribution":"Text-CSV_XS","first":"","maturity":"released","release":"Text-CSV_XS-0.17","status":"cpan","version":"0.17"},{"abstract":"v.0.21 General purpose text/data merging methods in Perl.","author":"SHARRIS","date":"1999-03-04T19:15:31","distribution":"Text-Merge","first":1,"maturity":"released","release":"Text-Merge-0.21","status":"backpan","version":"0.21"},{"abstract":"A perl module for parsing XML documents","author":"CNANDOR","date":"1999-03-04T18:21:15","distribution":"XML-Parser","first":"","maturity":"released","release":"XML-Parser-2.20-bin-1-Mac","status":"backpan","version":"2.20"},{"abstract":"Tie class for a simple ASCII database","author":"JOSERODR","date":"1999-03-04T18:16:37","distribution":"AsciiDB-TagFile","first":"","maturity":"released","release":"AsciiDB-TagFile-1.05","status":"backpan","version":"1.05"},{"abstract":"a Perl implementation of a finger client.","author":"FIMM","date":"1999-03-04T17:04:15","distribution":"Net-Finger","first":"","maturity":"released","release":"Net-Finger-1.04","status":"cpan","version":"1.04"},{"abstract":"a tool to help change your DNS settings","author":"RANDYM","date":"1999-03-04T16:38:35","distribution":"CfgTie","first":1,"maturity":"released","release":"CfgTie-0.2","status":"backpan","version":"0.2"},{"abstract":null,"author":"STBEY","date":"1999-03-04T16:03:48","distribution":"gen_tree","first":"","maturity":"released","release":"gen_tree-2.2","status":"backpan","version":"2.2"},{"abstract":"Support for Perl embedded in GNU Emacs","author":"JTOBEY","date":"1999-03-04T07:41:21","distribution":"Emacs-Lisp","first":"","maturity":"released","release":"Emacs-Lisp-0.79","status":"backpan","version":"0.79"},{"abstract":"Suite of modules to themeify a website","author":"JSMITH","date":"1999-03-04T05:19:21","distribution":"CGI-WeT","first":"","maturity":"released","release":"CGI-WeT-0.6","status":"backpan","version":"0.6"},{"abstract":"Compute `intelligent' differences between two files / lists","author":"MJD","date":"1999-03-04T05:16:20","distribution":"Algorithm-Diff","first":1,"maturity":"released","release":"Algorithm-Diff-0.56","status":"backpan","version":"0.56"},{"abstract":"Compute `intelligent' differences between two files / lists","author":"MJD","date":"1999-03-04T05:08:24","distribution":"Algorithm-Diff","first":"","maturity":"released","release":"Algorithm-Diff-0.57","status":"backpan","version":"0.57"},{"abstract":"Extract delimited text sequences from strings.","author":"DCONWAY","date":"1999-03-04T01:46:17","distribution":"Text-Balanced","first":"","maturity":"released","release":"Text-Balanced-1.52","status":"backpan","version":"1.52"},{"abstract":"A persistence framework for session data","author":"JBAKER","date":"1999-03-03T23:57:45","distribution":"Apache-Session","first":"","maturity":"released","release":"Apache-Session-0.99.7","status":"backpan","version":"v0.99.7"},{"abstract":null,"author":"SBURKE","date":"1999-03-03T19:11:12","distribution":"Games-Worms","first":1,"maturity":"released","release":"Games-Worms-0.60","status":"backpan","version":"0.60"},{"abstract":null,"author":"JHOWELL","date":"1999-03-03T18:51:24","distribution":"FAQ-OMatic","first":"","maturity":"released","release":"FAQ-OMatic-2.619","status":"cpan","version":"2.619"},{"abstract":"A class for passing event data between subroutines","author":"FIMM","date":"1999-03-03T17:51:40","distribution":"Net-IRC","first":"","maturity":"released","release":"Net-IRC-0.57","status":"cpan","version":"0.57"},{"abstract":"a Perl implementation of a finger client.","author":"FIMM","date":"1999-03-03T17:50:01","distribution":"Net-Finger","first":"","maturity":"released","release":"Net-Finger-1.03","status":"cpan","version":"1.03"},{"abstract":"Perl extension for statvfs().","author":"IGUTHRIE","date":"1999-03-03T15:35:44","distribution":"Filesys-Statvfs_Df","first":"","maturity":"released","release":"Filesys-Statvfs_Df-0.54","status":"backpan","version":"0.54"},{"abstract":"Perl extension to read variable blocked files from MVS","author":"GROMMEL","date":"1999-03-03T14:21:41","distribution":"MVS-VBFile","first":1,"maturity":"released","release":"MVS-VBFile-0.01","status":"backpan","version":"0.01"},{"abstract":null,"author":"PVERD","date":"1999-03-03T13:09:15","distribution":"RTF-Parser","first":"","maturity":"released","release":"RTF-Parser-1.05","status":"cpan","version":"1.05"},{"abstract":"Library for PDF access and manipulation in Perl","author":"ANTRO","date":"1999-03-03T12:05:40","distribution":"PDF","first":"","maturity":"released","release":"PDF-109","status":"cpan","version":"109"},{"abstract":"Support for Perl embedded in GNU Emacs","author":"JTOBEY","date":"1999-03-03T08:24:59","distribution":"Emacs-Lisp","first":"","maturity":"released","release":"Emacs-Lisp-0.78","status":"backpan","version":"0.78"},{"abstract":"Perl extension for calling ImageMagick's libmagick routines","author":"JCRISTY","date":"1999-03-02T19:37:45","distribution":"PerlMagick","first":"","maturity":"released","release":"PerlMagick-4.21","status":"backpan","version":"4.21"},{"abstract":"Solaris performance data collection and graphing package","author":"ABURLISON","date":"1999-03-02T18:55:32","distribution":"StatsView","first":"","maturity":"released","release":"StatsView-1.0","status":"backpan","version":"1.0"},{"abstract":"map between instance numbers and device names","author":"ABURLISON","date":"1999-03-02T18:54:00","distribution":"Solaris","first":"","maturity":"released","release":"Solaris-0.05","status":"backpan","version":"0.05"},{"abstract":null,"author":"ABURLISON","date":"1999-03-02T18:53:54","distribution":"Explain","first":"","maturity":"released","release":"Explain-1.0","status":"backpan","version":"1.0"},{"abstract":"Shuffle a list.","author":"ABIGAIL","date":"1999-03-01T21:18:46","distribution":"Shuffle","first":"","maturity":"released","release":"Shuffle-1.3","status":"backpan","version":"1.3"},{"abstract":"Draw samples from a set","author":"ABIGAIL","date":"1999-03-01T21:18:40","distribution":"Sample","first":1,"maturity":"released","release":"Sample-1.2","status":"backpan","version":"1.2"},{"abstract":"Calculate the transitive closure.","author":"ABIGAIL","date":"1999-03-01T21:17:04","distribution":"TransitiveClosure","first":"","maturity":"released","release":"TransitiveClosure-1.4","status":"backpan","version":"1.4"},{"abstract":"an API to the Perl weak references","author":"LUKKA","date":"1999-03-01T19:32:59","distribution":"WeakRef","first":1,"maturity":"released","release":"WeakRef-0.01","status":"latest","version":"0.01"},{"abstract":"Manage Unix crypt-style password file.","author":"KMELTZ","date":"1999-03-01T17:20:22","distribution":"Apache-Htpassword","first":1,"maturity":"released","release":"Apache-Htpassword-1.2","status":"backpan","version":"1.2"},{"abstract":"Report generator.","author":"RVAZ","date":"1999-03-01T15:18:17","distribution":"Data-Reporter","first":"","maturity":"released","release":"Data-Reporter-1.2","status":"cpan","version":"1.2"},{"abstract":"Manipulate / fetch info from MP3 audio files","author":"CNANDOR","date":"1999-03-01T14:34:11","distribution":"MPEG-MP3Info","first":"","maturity":"released","release":"MPEG-MP3Info-0.61","status":"backpan","version":"0.61"},{"abstract":"Perl/Tk module for message and button dialogue boxes.","author":"SUMMER","date":"1999-03-01T08:22:32","distribution":"pixmaped","first":1,"maturity":"released","release":"pixmaped-1.00","status":"backpan","version":"1.00"},{"abstract":"Perl/Tk module for message and button dialogue boxes.","author":"SUMMER","date":"1999-03-01T08:22:31","distribution":"snake","first":1,"maturity":"released","release":"snake-1.05","status":"backpan","version":"1.05"},{"abstract":"Perl/Tk module for message and button dialogue boxes.","author":"SUMMER","date":"1999-03-01T08:22:30","distribution":"petris","first":1,"maturity":"released","release":"petris-1.05","status":"backpan","version":"1.05"},{"abstract":"Perl module to fix the case of people's names.","author":"SUMMER","date":"1999-03-01T08:20:53","distribution":"NameCase","first":1,"maturity":"released","release":"NameCase-1.00","status":"backpan","version":"1.00"},{"abstract":"Perl module providing 3-value logic versions of \"and\", \"or\", \"xor\" and \"not\".","author":"SUMMER","date":"1999-03-01T08:20:52","distribution":"Logic3","first":1,"maturity":"released","release":"Logic3-1.01","status":"backpan","version":"1.01"},{"abstract":"Perl/Tk module providing a Colour selection dialogue box.","author":"SUMMER","date":"1999-03-01T08:19:19","distribution":"ColourChooser","first":1,"maturity":"released","release":"ColourChooser-1.08","status":"backpan","version":"1.08"},{"abstract":"A persistence framework for session data","author":"JBAKER","date":"1999-03-01T05:57:39","distribution":"Apache-Session","first":"","maturity":"released","release":"Apache-Session-0.99.6","status":"backpan","version":"v0.99.6"},{"abstract":"Perl pragma to control optional warnings","author":"GSAR","date":"1999-03-01T05:38:00","distribution":"perl","first":"","maturity":"developer","release":"perl5.005_56","status":"backpan","version":"5.005_56"},{"abstract":null,"author":"KJALB","date":"1999-03-01T05:05:50","distribution":"Devel-PPPort","first":1,"maturity":"released","release":"Devel-PPPort-1.0004","status":"cpan","version":"1.0004"},{"abstract":"A bundle of the modules nice to have for MiniVend, plus MiniVend itself;","author":"MIKEH","date":"1999-03-01T04:22:06","distribution":"Bundle-Minivend","first":"","maturity":"released","release":"Bundle-Minivend-0.02","status":"backpan","version":"0.02"}],{"func.num_rows":275,"stream":0,"table.fields":["release","date","author","status","maturity","version","first","distribution","abstract"]}]
